swimbundle_email/__init__.py
swimbundle_email/util.py
swimbundle_email-0.2.1.dist-info/METADATA
swimbundle_email-0.2.1.dist-info/RECORD
swimbundle_email-0.2.1.dist-info/WHEEL
swimbundle_email-0.2.1.dist-info/top_level.txt
